async_dfd/__init__.py
async_dfd/exceptions.py
async_dfd/label.py
async_dfd/analyser/__init__.py
async_dfd/analyser/analyser.py
async_dfd/analyser/monitor.py
async_dfd/analyser/pipeline_analyser.py
async_dfd/analyser/singleton_meta.py
async_dfd/node/__init__.py
async_dfd/node/abstract_node.py
async_dfd/node/decorator.py
async_dfd/node/node.py
async_dfd/node/node_link.py
async_dfd/node_group/__init__.py
async_dfd/node_group/graph.py
async_dfd/node_group/node_group.py
async_dfd/node_group/pipeline.py
async_dfd/node_group/sequential.py
async_dfd/node_group/special_pipeline/__init__.py
async_dfd/node_group/special_pipeline/cycle_pipeline.py
async_dfd/node_group/special_pipeline/iterable_pipeline.py
async_dfd/node_group/special_pipeline/label_pipeline.py
async_dfd/node_group/special_pipeline/order_pipeline.py
test/node/test_node.py
async_dfd-0.1.16.dist-info/LICENSE
async_dfd-0.1.16.dist-info/METADATA
async_dfd-0.1.16.dist-info/WHEEL
async_dfd-0.1.16.dist-info/top_level.txt
async_dfd-0.1.16.dist-info/RECORD
